caniuse/main.py
caniuse/cli.py
caniuse/__init__.py
caniuse/test/test_caniuse.py
caniuse/test/__pycache__/test_caniuse.cpython-33-PYTEST.pyc
caniuse/test/__pycache__/test_caniuse.cpython-27-PYTEST.pyc
caniuse-0.3.1.dist-info/entry_points.txt
caniuse-0.3.1.dist-info/METADATA
caniuse-0.3.1.dist-info/WHEEL
caniuse-0.3.1.dist-info/RECORD
caniuse-0.3.1.dist-info/top_level.txt
caniuse-0.3.1.dist-info/metadata.json
caniuse-0.3.1.dist-info/DESCRIPTION.rst
