Metadata-Version: 2.0
Name: caniuse
Version: 0.3.1
Summary: check whether a package name has been used on PyPI.
Home-page: http://github.com/lord63/caniuse
Author: lord63
Author-email: lord63.j@gmail.com
License: MIT
Keywords: PyPI package name used registered
Platform: UNKNOWN
Classifier: Development Status :: 4 - Beta
Classifier: Operating System :: POSIX
Classifier: Operating System :: POSIX :: Linux
Classifier: License :: OSI Approved :: MIT License
Classifier: Programming Language :: Python :: 2
Classifier: Programming Language :: Python :: 2.7
Classifier: Programming Language :: Python :: 3
Classifier: Programming Language :: Python :: 3.3
Classifier: Programming Language :: Python :: 3.4
Classifier: Programming Language :: Python :: 3.5
Requires-Dist: click (>=4.0)
Requires-Dist: requests (>=2.7.0)
